Workbook

Sheet Risk Register
A1: Information Security Risk Register: Sample (Fictional Company: Northwind Health Tech, Cloud SaaS)
A2: Sample for portfolio use. All data is fictional. Blue = input, black = formula. Scales and thresholds are on the 'Scoring Criteria' tab.
A3: © 2026 Hina Qurashee. All rights reserved.
A4: Risk ID | B4: Risk Description (If / Then / Resulting in) | C4: Category | D4: Affected Asset / Process | E4: Likelihood (1-5) | F4: Impact (1-5) | G4: Inherent Score | H4: Inherent Rating | I4: Control Reference (ISO 27001:2022 / NIST CSF) | J4: Treatment | K4: Mitigation Actions | L4: Risk Owner | M4: Due Date | N4: Status | O4: Residual Likelihood | P4: Residual Impact | Q4: Residual Score | R4: Residual Rating
A5: R-001 | B5: If privileged accounts lack MFA, then credential theft could allow database access, resulting in a PHI breach, HIPAA penalties and loss of customers. | C5: Cybersecurity | D5: Customer PHI database | E5: 3 | F5: 5 | G5: =E5*F5 -> 15 | H5: =IF(G5>='Scoring Criteria'!$B$13,"Critical",IF(G5>='Scoring Criteria'!$B$14,"High",IF(G5>='Scoring Criteria'!$B$15,"Medium","Low"))) -> High | I5: A.5.17, A.8.5 / PR.AA | J5: Mitigate | K5: Enforce phishing-resistant MFA on all admin accounts; quarterly privileged access review. | L5: CISO | M5: 46356 | N5: In Progress | O5: 2 | P5: 5 | Q5: =O5*P5 -> 10 | R5: =IF(Q5>='Scoring Criteria'!$B$13,"Critical",IF(Q5>='Scoring Criteria'!$B$14,"High",IF(Q5>='Scoring Criteria'!$B$15,"Medium","Low"))) -> Medium
A6: R-002 | B6: If vendors are not assessed before onboarding, then weak vendor controls could expose shared data, resulting in a reportable incident and contract liability. | C6: Third-Party | D6: Payment and analytics vendors | E6: 4 | F6: 4 | G6: =E6*F6 -> 16 | H6: =IF(G6>='Scoring Criteria'!$B$13,"Critical",IF(G6>='Scoring Criteria'!$B$14,"High",IF(G6>='Scoring Criteria'!$B$15,"Medium","Low"))) -> High | I6: A.5.19, A.5.22 / GV.SC | J6: Mitigate | K6: Implement tiered vendor due diligence (questionnaire, SOC 2 review) and annual reassessment. | L6: Vendor Risk Manager | M6: 46371 | N6: Open | O6: 3 | P6: 3 | Q6: =O6*P6 -> 9 | R6: =IF(Q6>='Scoring Criteria'!$B$13,"Critical",IF(Q6>='Scoring Criteria'!$B$14,"High",IF(Q6>='Scoring Criteria'!$B$15,"Medium","Low"))) -> Medium
A7: R-003 | B7: If backups are not tested, then restoration could fail after ransomware or outage, resulting in extended downtime and SLA breach. | C7: Operational | D7: Production cloud environment | E7: 3 | F7: 5 | G7: =E7*F7 -> 15 | H7: =IF(G7>='Scoring Criteria'!$B$13,"Critical",IF(G7>='Scoring Criteria'!$B$14,"High",IF(G7>='Scoring Criteria'!$B$15,"Medium","Low"))) -> High | I7: A.8.13, A.5.30 / PR.DS, RC.RP | J7: Mitigate | K7: Run quarterly restore tests; keep immutable offsite backups; document RTO/RPO. | L7: IT Operations Manager | M7: 46341 | N7: In Progress | O7: 2 | P7: 4 | Q7: =O7*P7 -> 8 | R7: =IF(Q7>='Scoring Criteria'!$B$13,"Critical",IF(Q7>='Scoring Criteria'!$B$14,"High",IF(Q7>='Scoring Criteria'!$B$15,"Medium","Low"))) -> Medium
A8: R-004 | B8: If the annual risk assessment and policy review lapse, then audit gaps could go unnoticed, resulting in findings and fines from regulators. | C8: Compliance | D8: HIPAA Security Rule program | E8: 3 | F8: 4 | G8: =E8*F8 -> 12 | H8: =IF(G8>='Scoring Criteria'!$B$13,"Critical",IF(G8>='Scoring Criteria'!$B$14,"High",IF(G8>='Scoring Criteria'!$B$15,"Medium","Low"))) -> High | I8: A.5.36, A.5.1 / GV.PO | J8: Mitigate | K8: Set annual compliance calendar; assign policy owners; track attestations in GRC tool. | L8: Compliance Manager | M8: 46326 | N8: Open | O8: 2 | P8: 3 | Q8: =O8*P8 -> 6 | R8: =IF(Q8>='Scoring Criteria'!$B$13,"Critical",IF(Q8>='Scoring Criteria'!$B$14,"High",IF(Q8>='Scoring Criteria'!$B$15,"Medium","Low"))) -> Medium
A9: R-005 | B9: If staff are not trained on phishing, then a malicious link could be clicked, resulting in malware infection and lateral movement. | C9: Cybersecurity | D9: Employee workstations and email | E9: 4 | F9: 3 | G9: =E9*F9 -> 12 | H9: =IF(G9>='Scoring Criteria'!$B$13,"Critical",IF(G9>='Scoring Criteria'!$B$14,"High",IF(G9>='Scoring Criteria'!$B$15,"Medium","Low"))) -> High | I9: A.6.3, A.8.7 / PR.AT | J9: Mitigate | K9: Monthly phishing simulations; role-based training; email filtering upgrade. | L9: Security Awareness Lead | M9: 46387 | N9: In Progress | O9: 3 | P9: 2 | Q9: =O9*P9 -> 6 | R9: =IF(Q9>='Scoring Criteria'!$B$13,"Critical",IF(Q9>='Scoring Criteria'!$B$14,"High",IF(Q9>='Scoring Criteria'!$B$15,"Medium","Low"))) -> Medium
A10: R-006 | B10: If patches are not applied within SLA, then known vulnerabilities could be exploited, resulting in service compromise or data loss. | C10: Cybersecurity | D10: Public-facing web application | E10: 4 | F10: 4 | G10: =E10*F10 -> 16 | H10: =IF(G10>='Scoring Criteria'!$B$13,"Critical",IF(G10>='Scoring Criteria'!$B$14,"High",IF(G10>='Scoring Criteria'!$B$15,"Medium","Low"))) -> High | I10: A.8.8 / ID.RA, PR.PS | J10: Mitigate | K10: Define patch SLAs by severity (critical within 7 days); weekly vulnerability scans; report KPI to leadership. | L10: Head of Engineering | M10: 46346 | N10: In Progress | O10: 2 | P10: 4 | Q10: =O10*P10 -> 8 | R10: =IF(Q10>='Scoring Criteria'!$B$13,"Critical",IF(Q10>='Scoring Criteria'!$B$14,"High",IF(Q10>='Scoring Criteria'!$B$15,"Medium","Low"))) -> Medium
A11: R-007 | B11: If data retention schedules are not enforced, then excess personal data could be held, resulting in a larger breach footprint and GDPR/CCPA exposure. | C11: Privacy | D11: Customer personal data | E11: 3 | F11: 3 | G11: =E11*F11 -> 9 | H11: =IF(G11>='Scoring Criteria'!$B$13,"Critical",IF(G11>='Scoring Criteria'!$B$14,"High",IF(G11>='Scoring Criteria'!$B$15,"Medium","Low"))) -> Medium | I11: A.5.33, A.8.10 / GV.PO | J11: Mitigate | K11: Publish retention schedule; automate deletion jobs; annual data inventory. | L11: Data Protection Officer | M11: 46418 | N11: Open | O11: 2 | P11: 2 | Q11: =O11*P11 -> 4 | R11: =IF(Q11>='Scoring Criteria'!$B$13,"Critical",IF(Q11>='Scoring Criteria'!$B$14,"High",IF(Q11>='Scoring Criteria'!$B$15,"Medium","Low"))) -> Low
A12: R-008 | B12: If there is no tested BCP/DR plan, then a regional outage could stall operations, resulting in prolonged downtime and revenue loss. | C12: Business Continuity | D12: Core platform and support operations | E12: 2 | F12: 5 | G12: =E12*F12 -> 10 | H12: =IF(G12>='Scoring Criteria'!$B$13,"Critical",IF(G12>='Scoring Criteria'!$B$14,"High",IF(G12>='Scoring Criteria'!$B$15,"Medium","Low"))) -> Medium | I12: A.5.29, A.5.30 / RC.RP | J12: Mitigate | K12: Complete business impact analysis; run annual tabletop and failover exercise. | L12: Business Continuity Lead | M12: 46446 | N12: Open | O12: 1 | P12: 4 | Q12: =O12*P12 -> 4 | R12: =IF(Q12>='Scoring Criteria'!$B$13,"Critical",IF(Q12>='Scoring Criteria'!$B$14,"High",IF(Q12>='Scoring Criteria'!$B$15,"Medium","Low"))) -> Low
A13: R-009 | B13: If access is not removed promptly on termination, then former staff could retain access, resulting in data theft or sabotage. | C13: Insider Threat | D13: Source code and customer data | E13: 3 | F13: 4 | G13: =E13*F13 -> 12 | H13: =IF(G13>='Scoring Criteria'!$B$13,"Critical",IF(G13>='Scoring Criteria'!$B$14,"High",IF(G13>='Scoring Criteria'!$B$15,"Medium","Low"))) -> High | I13: A.6.5, A.5.18 / PR.AA | J13: Mitigate | K13: Automate offboarding via HR-IdP integration; monthly access reconciliation. | L13: HR Director / IT Manager | M13: 46336 | N13: In Progress | O13: 1 | P13: 4 | Q13: =O13*P13 -> 4 | R13: =IF(Q13>='Scoring Criteria'!$B$13,"Critical",IF(Q13>='Scoring Criteria'!$B$14,"High",IF(Q13>='Scoring Criteria'!$B$15,"Medium","Low"))) -> Low
A14: R-010 | B14: If the incident response plan is untested, then response to a breach could be slow, resulting in missed 60-day notification deadlines and higher costs. | C14: Cybersecurity | D14: Incident response capability | E14: 3 | F14: 4 | G14: =E14*F14 -> 12 | H14: =IF(G14>='Scoring Criteria'!$B$13,"Critical",IF(G14>='Scoring Criteria'!$B$14,"High",IF(G14>='Scoring Criteria'!$B$15,"Medium","Low"))) -> High | I14: A.5.24, A.5.26 / RS.MA | J14: Mitigate | K14: Update IR plan and playbooks; run semi-annual tabletop; retain external IR firm. | L14: CISO | M14: 46366 | N14: Open | O14: 2 | P14: 3 | Q14: =O14*P14 -> 6 | R14: =IF(Q14>='Scoring Criteria'!$B$13,"Critical",IF(Q14>='Scoring Criteria'!$B$14,"High",IF(Q14>='Scoring Criteria'!$B$15,"Medium","Low"))) -> Medium
A15: R-011 | B15: If an unsupported OS stays in service, then unpatched flaws could be exploited, resulting in compromise of billing data. | C15: Technology | D15: Legacy on-prem billing server | E15: 4 | F15: 3 | G15: =E15*F15 -> 12 | H15: =IF(G15>='Scoring Criteria'!$B$13,"Critical",IF(G15>='Scoring Criteria'!$B$14,"High",IF(G15>='Scoring Criteria'!$B$15,"Medium","Low"))) -> High | I15: A.8.8, A.8.9 / ID.AM | J15: Avoid | K15: Migrate billing workload to supported cloud platform and decommission server. | L15: Head of Engineering | M15: 46477 | N15: Open | O15: 1 | P15: 3 | Q15: =O15*P15 -> 3 | R15: =IF(Q15>='Scoring Criteria'!$B$13,"Critical",IF(Q15>='Scoring Criteria'!$B$14,"High",IF(Q15>='Scoring Criteria'!$B$15,"Medium","Low"))) -> Low
A16: R-012 | B16: If cyber insurance limits are below realistic loss, then a major breach could exceed coverage, resulting in uninsured financial loss. | C16: Financial | D16: Cyber liability coverage | E16: 2 | F16: 4 | G16: =E16*F16 -> 8 | H16: =IF(G16>='Scoring Criteria'!$B$13,"Critical",IF(G16>='Scoring Criteria'!$B$14,"High",IF(G16>='Scoring Criteria'!$B$15,"Medium","Low"))) -> Medium | I16: GV.RM | J16: Transfer | K16: Review coverage limits against breach cost modeling; renew policy with adequate limits. | L16: CFO | M16: 46387 | N16: Open | O16: 2 | P16: 3 | Q16: =O16*P16 -> 6 | R16: =IF(Q16>='Scoring Criteria'!$B$13,"Critical",IF(Q16>='Scoring Criteria'!$B$14,"High",IF(Q16>='Scoring Criteria'!$B$15,"Medium","Low"))) -> Medium
... A18: R-014 | B18: If physical access controls are weak, then unauthorized entry could occur, resulting in equipment theft or tampering. | C18: Physical | D18: Office server closet | E18: 2 | F18: 3 | G18: =E18*F18 -> 6 | H18: =IF(G18>='Scoring Criteria'!$B$13,"Critical",IF(G18>='Scoring Criteria'!$B$14,"High",IF(G18>='Scoring Criteria'!$B$15,"Medium","Low"))) -> Medium | I18: A.7.2, A.7.4 / PR.AA | J18: Accept | K18: Accept with existing badge access and CCTV; review access list annually. | L18: Facilities Manager | M18: 46568 | N18: Accepted | O18: 2 | P18: 3 | Q18: =O18*P18 -> 6 | R18: =IF(Q18>='Scoring Criteria'!$B$13,"Critical",IF(Q18>='Scoring Criteria'!$B$14,"High",IF(Q18>='Scoring Criteria'!$B$15,"Medium","Low"))) -> Medium
A20: Assumptions: scores are illustrative judgments for a fictional company; control references map to ISO/IEC 27001:2022 Annex A and NIST CSF 2.0 functions; owners are roles, not named people.

Sheet Scoring Criteria
A1: Scoring Criteria & Risk Appetite
A2: Score = Likelihood x Impact (1-25). Thresholds below drive the Rating column on the Risk Register.
A4: Score | B4: Likelihood | C4: Impact
A5: 1 | B5: Rare: <5% chance in 12 months | C5: Negligible: no customer impact, <$10K loss
A6: 2 | B6: Unlikely: 5-20% | C6: Minor: limited internal disruption, $10K-$50K
A7: 3 | B7: Possible: 20-50% | C7: Moderate: some customer impact, minor regulatory notice, $50K-$250K
A8: 4 | B8: Likely: 50-80% | C8: Major: significant outage or data exposure, regulatory action, $250K-$1M
A9: 5 | B9: Almost certain: >80% | C9: Severe: large breach, loss of key customers or license, >$1M
A11: Rating Thresholds (editable inputs)
A12: Rating | B12: Minimum Score | C12: Required Action
A13: Critical | B13: 20 | C13: Escalate to executive leadership; treat immediately
A14: High | B14: 12 | C14: Treatment plan required within 30 days; monthly review
A15: Medium | B15: 6 | C15: Treatment plan within 90 days; quarterly review
A16: Low | B16: 1 | C16: Accept and monitor; annual review
A18: Note: scales and thresholds are illustrative assumptions for this sample, loosely modeled on common NIST SP 800-30 / ISO 27005 practice. Blue = editable input.
A20: © 2026 Hina Qurashee. All rights reserved.

Sheet Heat Map
A1: Inherent Risk Heat Map (count of risks)
A2: Counts update automatically from the Risk Register.
A4: Likelihood \ Impact | B4: 1 | C4: 2 | D4: 3 | E4: 4 | F4: 5
A5: 5 | B5: =COUNTIFS('Risk Register'!$E$5:$E$18,$A5,'Risk Register'!$F$5:$F$18,B$4) -> 0 | C5: =COUNTIFS('Risk Register'!$E$5:$E$18,$A5,'Risk Register'!$F$5:$F$18,C$4) -> 0 | D5: =COUNTIFS('Risk Register'!$E$5:$E$18,$A5,'Risk Register'!$F$5:$F$18,D$4) -> 0 | E5: =COUNTIFS('Risk Register'!$E$5:$E$18,$A5,'Risk Register'!$F$5:$F$18,E$4) -> 0 | F5: =COUNTIFS('Risk Register'!$E$5:$E$18,$A5,'Risk Register'!$F$5:$F$18,F$4) -> 0
A6: 4 | B6: =COUNTIFS('Risk Register'!$E$5:$E$18,$A6,'Risk Register'!$F$5:$F$18,B$4) -> 0 | C6: =COUNTIFS('Risk Register'!$E$5:$E$18,$A6,'Risk Register'!$F$5:$F$18,C$4) -> 0 | D6: =COUNTIFS('Risk Register'!$E$5:$E$18,$A6,'Risk Register'!$F$5:$F$18,D$4) -> 2 | E6: =COUNTIFS('Risk Register'!$E$5:$E$18,$A6,'Risk Register'!$F$5:$F$18,E$4) -> 2 | F6: =COUNTIFS('Risk Register'!$E$5:$E$18,$A6,'Risk Register'!$F$5:$F$18,F$4) -> 0
A7: 3 | B7: =COUNTIFS('Risk Register'!$E$5:$E$18,$A7,'Risk Register'!$F$5:$F$18,B$4) -> 0 | C7: =COUNTIFS('Risk Register'!$E$5:$E$18,$A7,'Risk Register'!$F$5:$F$18,C$4) -> 0 | D7: =COUNTIFS('Risk Register'!$E$5:$E$18,$A7,'Risk Register'!$F$5:$F$18,D$4) -> 1 | E7: =COUNTIFS('Risk Register'!$E$5:$E$18,$A7,'Risk Register'!$F$5:$F$18,E$4) -> 4 | F7: =COUNTIFS('Risk Register'!$E$5:$E$18,$A7,'Risk Register'!$F$5:$F$18,F$4) -> 2
A8: 2 | B8: =COUNTIFS('Risk Register'!$E$5:$E$18,$A8,'Risk Register'!$F$5:$F$18,B$4) -> 0 | C8: =COUNTIFS('Risk Register'!$E$5:$E$18,$A8,'Risk Register'!$F$5:$F$18,C$4) -> 0 | D8: =COUNTIFS('Risk Register'!$E$5:$E$18,$A8,'Risk Register'!$F$5:$F$18,D$4) -> 1 | E8: =COUNTIFS('Risk Register'!$E$5:$E$18,$A8,'Risk Register'!$F$5:$F$18,E$4) -> 1 | F8: =COUNTIFS('Risk Register'!$E$5:$E$18,$A8,'Risk Register'!$F$5:$F$18,F$4) -> 1
A9: 1 | B9: =COUNTIFS('Risk Register'!$E$5:$E$18,$A9,'Risk Register'!$F$5:$F$18,B$4) -> 0 | C9: =COUNTIFS('Risk Register'!$E$5:$E$18,$A9,'Risk Register'!$F$5:$F$18,C$4) -> 0 | D9: =COUNTIFS('Risk Register'!$E$5:$E$18,$A9,'Risk Register'!$F$5:$F$18,D$4) -> 0 | E9: =COUNTIFS('Risk Register'!$E$5:$E$18,$A9,'Risk Register'!$F$5:$F$18,E$4) -> 0 | F9: =COUNTIFS('Risk Register'!$E$5:$E$18,$A9,'Risk Register'!$F$5:$F$18,F$4) -> 0
A11: Summary by Rating
A12: Rating | B12: Inherent | C12: Residual
A13: Critical | B13: =COUNTIF('Risk Register'!$H$5:$H$18,A13) -> 0 | C13: =COUNTIF('Risk Register'!$R$5:$R$18,A13) -> 0
A14: High | B14: =COUNTIF('Risk Register'!$H$5:$H$18,A14) -> 10 | C14: =COUNTIF('Risk Register'!$R$5:$R$18,A14) -> 0
A15: Medium | B15: =COUNTIF('Risk Register'!$H$5:$H$18,A15) -> 4 | C15: =COUNTIF('Risk Register'!$R$5:$R$18,A15) -> 9
A16: Low | B16: =COUNTIF('Risk Register'!$H$5:$H$18,A16) -> 0 | C16: =COUNTIF('Risk Register'!$R$5:$R$18,A16) -> 5
A17: Total | B17: =SUM(B13:B16) -> 14 | C17: =SUM(C13:C16) -> 14
A18: Average Score | B18: =AVERAGE('Risk Register'!G5:G18) -> 11.928571 | C18: =AVERAGE('Risk Register'!Q5:Q18) -> 6
A20: © 2026 Hina Qurashee. All rights reserved.
